{
    "imgHeight": 1024, 
    "imgWidth": 2048, 
    "objects": [
        {
            "instanceId": 0, 
            "bbox": [
                497, 
                331, 
                79, 
                78
            ], 
            "bboxVis": [
                497, 
                331, 
                79, 
                78
            ], 
            "label": "ignore"
        }, 
        {
            "instanceId": 0, 
            "bbox": [
                592, 
                349, 
                60, 
                63
            ], 
            "bboxVis": [
                592, 
                349, 
                60, 
                63
            ], 
            "label": "ignore"
        }, 
        {
            "instanceId": 0, 
            "bbox": [
                677, 
                349, 
                74, 
                67
            ], 
            "bboxVis": [
                677, 
                349, 
                74, 
                67
            ], 
            "label": "ignore"
        }, 
        {
            "instanceId": 0, 
            "bbox": [
                766, 
                358, 
                102, 
                132
            ], 
            "bboxVis": [
                766, 
                358, 
                102, 
                132
            ], 
            "label": "ignore"
        }, 
        {
            "instanceId": 0, 
            "bbox": [
                890, 
                346, 
                116, 
                149
            ], 
            "bboxVis": [
                890, 
                346, 
                116, 
                149
            ], 
            "label": "ignore"
        }, 
        {
            "instanceId": 0, 
            "bbox": [
                1207, 
                381, 
                14, 
                32
            ], 
            "bboxVis": [
                1207, 
                381, 
                14, 
                32
            ], 
            "label": "ignore"
        }
    ]
}