{
    "imgHeight": 1024, 
    "imgWidth": 2048, 
    "objects": [
        {
            "instanceId": 24000, 
            "bbox": [
                733, 
                458, 
                10, 
                24
            ], 
            "bboxVis": [
                734, 
                460, 
                9, 
                22
            ], 
            "label": "pedestrian"
        }, 
        {
            "instanceId": 24001, 
            "bbox": [
                722, 
                460, 
                9, 
                23
            ], 
            "bboxVis": [
                724, 
                460, 
                7, 
                23
            ], 
            "label": "pedestrian"
        }, 
        {
            "instanceId": 24002, 
            "bbox": [
                704, 
                459, 
                11, 
                27
            ], 
            "bboxVis": [
                704, 
                459, 
                11, 
                27
            ], 
            "label": "pedestrian"
        }, 
        {
            "instanceId": 24003, 
            "bbox": [
                745, 
                459, 
                10, 
                23
            ], 
            "bboxVis": [
                745, 
                460, 
                10, 
                22
            ], 
            "label": "pedestrian"
        }, 
        {
            "instanceId": 24004, 
            "bbox": [
                1904, 
                353, 
                53, 
                129
            ], 
            "bboxVis": [
                1913, 
                354, 
                43, 
                128
            ], 
            "label": "pedestrian"
        }, 
        {
            "instanceId": 24005, 
            "bbox": [
                1962, 
                407, 
                30, 
                73
            ], 
            "bboxVis": [
                1962, 
                407, 
                30, 
                73
            ], 
            "label": "pedestrian"
        }, 
        {
            "instanceId": 0, 
            "bbox": [
                1830, 
                327, 
                70, 
                67
            ], 
            "bboxVis": [
                1830, 
                327, 
                70, 
                67
            ], 
            "label": "ignore"
        }, 
        {
            "instanceId": 0, 
            "bbox": [
                1785, 
                367, 
                43, 
                132
            ], 
            "bboxVis": [
                1785, 
                367, 
                43, 
                132
            ], 
            "label": "ignore"
        }, 
        {
            "instanceId": 0, 
            "bbox": [
                1433, 
                369, 
                11, 
                14
            ], 
            "bboxVis": [
                1433, 
                369, 
                11, 
                14
            ], 
            "label": "ignore"
        }, 
        {
            "instanceId": 0, 
            "bbox": [
                1345, 
                397, 
                17, 
                29
            ], 
            "bboxVis": [
                1345, 
                397, 
                17, 
                29
            ], 
            "label": "ignore"
        }, 
        {
            "instanceId": 0, 
            "bbox": [
                1352, 
                428, 
                9, 
                29
            ], 
            "bboxVis": [
                1352, 
                428, 
                9, 
                29
            ], 
            "label": "ignore"
        }, 
        {
            "instanceId": 0, 
            "bbox": [
                1238, 
                441, 
                14, 
                14
            ], 
            "bboxVis": [
                1238, 
                441, 
                14, 
                14
            ], 
            "label": "ignore"
        }, 
        {
            "instanceId": 0, 
            "bbox": [
                1239, 
                423, 
                9, 
                13
            ], 
            "bboxVis": [
                1239, 
                423, 
                9, 
                13
            ], 
            "label": "ignore"
        }, 
        {
            "instanceId": 0, 
            "bbox": [
                474, 
                438, 
                19, 
                24
            ], 
            "bboxVis": [
                474, 
                438, 
                19, 
                24
            ], 
            "label": "ignore"
        }, 
        {
            "instanceId": 0, 
            "bbox": [
                477, 
                466, 
                16, 
                21
            ], 
            "bboxVis": [
                477, 
                466, 
                16, 
                21
            ], 
            "label": "ignore"
        }, 
        {
            "instanceId": 0, 
            "bbox": [
                776, 
                455, 
                15, 
                25
            ], 
            "bboxVis": [
                776, 
                455, 
                15, 
                25
            ], 
            "label": "ignore"
        }
    ]
}