{
    "imgHeight": 1024, 
    "imgWidth": 2048, 
    "objects": [
        {
            "instanceId": 24000, 
            "bbox": [
                579, 
                415, 
                39, 
                95
            ], 
            "bboxVis": [
                589, 
                415, 
                26, 
                95
            ], 
            "label": "pedestrian"
        }, 
        {
            "instanceId": 24001, 
            "bbox": [
                549, 
                414, 
                41, 
                99
            ], 
            "bboxVis": [
                554, 
                414, 
                36, 
                99
            ], 
            "label": "pedestrian"
        }, 
        {
            "instanceId": 24002, 
            "bbox": [
                179, 
                428, 
                36, 
                89
            ], 
            "bboxVis": [
                186, 
                428, 
                29, 
                89
            ], 
            "label": "pedestrian"
        }, 
        {
            "instanceId": 24003, 
            "bbox": [
                148, 
                421, 
                41, 
                99
            ], 
            "bboxVis": [
                153, 
                421, 
                36, 
                99
            ], 
            "label": "pedestrian"
        }, 
        {
            "instanceId": 24004, 
            "bbox": [
                364, 
                420, 
                39, 
                92
            ], 
            "bboxVis": [
                369, 
                420, 
                34, 
                92
            ], 
            "label": "pedestrian"
        }, 
        {
            "instanceId": 24005, 
            "bbox": [
                338, 
                424, 
                49, 
                118
            ], 
            "bboxVis": [
                339, 
                425, 
                41, 
                117
            ], 
            "label": "pedestrian"
        }, 
        {
            "instanceId": 24006, 
            "bbox": [
                930, 
                414, 
                35, 
                86
            ], 
            "bboxVis": [
                937, 
                414, 
                22, 
                86
            ], 
            "label": "pedestrian"
        }, 
        {
            "instanceId": 24007, 
            "bbox": [
                884, 
                406, 
                38, 
                95
            ], 
            "bboxVis": [
                889, 
                406, 
                33, 
                95
            ], 
            "label": "pedestrian"
        }, 
        {
            "instanceId": 24008, 
            "bbox": [
                858, 
                418, 
                33, 
                81
            ], 
            "bboxVis": [
                861, 
                425, 
                26, 
                74
            ], 
            "label": "pedestrian"
        }, 
        {
            "instanceId": 24009, 
            "bbox": [
                763, 
                404, 
                46, 
                113
            ], 
            "bboxVis": [
                767, 
                405, 
                34, 
                112
            ], 
            "label": "pedestrian"
        }, 
        {
            "instanceId": 24010, 
            "bbox": [
                792, 
                404, 
                47, 
                113
            ], 
            "bboxVis": [
                798, 
                404, 
                31, 
                113
            ], 
            "label": "pedestrian"
        }, 
        {
            "instanceId": 24011, 
            "bbox": [
                811, 
                408, 
                47, 
                115
            ], 
            "bboxVis": [
                825, 
                408, 
                33, 
                115
            ], 
            "label": "pedestrian"
        }, 
        {
            "instanceId": 24012, 
            "bbox": [
                1007, 
                411, 
                36, 
                87
            ], 
            "bboxVis": [
                1007, 
                411, 
                36, 
                87
            ], 
            "label": "pedestrian"
        }, 
        {
            "instanceId": 24013, 
            "bbox": [
                1066, 
                394, 
                65, 
                119
            ], 
            "bboxVis": [
                1066, 
                394, 
                65, 
                119
            ], 
            "label": "sitting person"
        }, 
        {
            "instanceId": 24014, 
            "bbox": [
                1637, 
                370, 
                56, 
                136
            ], 
            "bboxVis": [
                1647, 
                370, 
                25, 
                20
            ], 
            "label": "pedestrian"
        }, 
        {
            "instanceId": 24015, 
            "bbox": [
                1738, 
                373, 
                52, 
                125
            ], 
            "bboxVis": [
                1740, 
                373, 
                31, 
                15
            ], 
            "label": "pedestrian"
        }, 
        {
            "instanceId": 24016, 
            "bbox": [
                1971, 
                374, 
                39, 
                95
            ], 
            "bboxVis": [
                1975, 
                374, 
                27, 
                66
            ], 
            "label": "pedestrian"
        }, 
        {
            "instanceId": 24017, 
            "bbox": [
                1834, 
                385, 
                35, 
                85
            ], 
            "bboxVis": [
                1839, 
                385, 
                30, 
                47
            ], 
            "label": "pedestrian"
        }, 
        {
            "instanceId": 25000, 
            "bbox": [
                1566, 
                361, 
                74, 
                181
            ], 
            "bboxVis": [
                1566, 
                361, 
                74, 
                181
            ], 
            "label": "rider"
        }, 
        {
            "instanceId": 0, 
            "bbox": [
                1907, 
                356, 
                22, 
                74
            ], 
            "bboxVis": [
                1907, 
                356, 
                22, 
                74
            ], 
            "label": "ignore"
        }, 
        {
            "instanceId": 0, 
            "bbox": [
                1853, 
                349, 
                34, 
                64
            ], 
            "bboxVis": [
                1853, 
                349, 
                34, 
                64
            ], 
            "label": "ignore"
        }, 
        {
            "instanceId": 0, 
            "bbox": [
                731, 
                423, 
                10, 
                18
            ], 
            "bboxVis": [
                731, 
                423, 
                10, 
                18
            ], 
            "label": "ignore"
        }, 
        {
            "instanceId": 0, 
            "bbox": [
                1110, 
                362, 
                59, 
                152
            ], 
            "bboxVis": [
                1110, 
                362, 
                59, 
                152
            ], 
            "label": "ignore"
        }, 
        {
            "instanceId": 24, 
            "bbox": [
                1048, 
                412, 
                43, 
                70
            ], 
            "bboxVis": [
                0, 
                0, 
                0, 
                0
            ], 
            "label": "person group"
        }, 
        {
            "instanceId": 24, 
            "bbox": [
                1171, 
                405, 
                60, 
                54
            ], 
            "bboxVis": [
                0, 
                0, 
                0, 
                0
            ], 
            "label": "person group"
        }, 
        {
            "instanceId": 24, 
            "bbox": [
                1238, 
                388, 
                328, 
                123
            ], 
            "bboxVis": [
                0, 
                0, 
                0, 
                0
            ], 
            "label": "person group"
        }
    ]
}