{
    "imgHeight": 1024, 
    "imgWidth": 2048, 
    "objects": [
        {
            "instanceId": 24000, 
            "bbox": [
                787, 
                435, 
                10, 
                24
            ], 
            "bboxVis": [
                789, 
                436, 
                8, 
                23
            ], 
            "label": "pedestrian"
        }, 
        {
            "instanceId": 24001, 
            "bbox": [
                780, 
                435, 
                10, 
                25
            ], 
            "bboxVis": [
                781, 
                435, 
                9, 
                25
            ], 
            "label": "pedestrian"
        }, 
        {
            "instanceId": 24002, 
            "bbox": [
                1087, 
                431, 
                24, 
                59
            ], 
            "bboxVis": [
                1087, 
                431, 
                24, 
                59
            ], 
            "label": "pedestrian"
        }, 
        {
            "instanceId": 24003, 
            "bbox": [
                1115, 
                428, 
                25, 
                60
            ], 
            "bboxVis": [
                1115, 
                428, 
                25, 
                60
            ], 
            "label": "pedestrian"
        }, 
        {
            "instanceId": 24004, 
            "bbox": [
                1137, 
                429, 
                24, 
                59
            ], 
            "bboxVis": [
                1142, 
                430, 
                19, 
                58
            ], 
            "label": "pedestrian"
        }, 
        {
            "instanceId": 24005, 
            "bbox": [
                1471, 
                414, 
                63, 
                156
            ], 
            "bboxVis": [
                1471, 
                415, 
                63, 
                155
            ], 
            "label": "pedestrian"
        }, 
        {
            "instanceId": 24006, 
            "bbox": [
                1533, 
                401, 
                70, 
                171
            ], 
            "bboxVis": [
                1536, 
                401, 
                67, 
                171
            ], 
            "label": "pedestrian"
        }
    ]
}