{
    "imgHeight": 1024, 
    "imgWidth": 2048, 
    "objects": [
        {
            "instanceId": 24000, 
            "bbox": [
                95, 
                288, 
                153, 
                374
            ], 
            "bboxVis": [
                99, 
                291, 
                117, 
                371
            ], 
            "label": "pedestrian"
        }, 
        {
            "instanceId": 24001, 
            "bbox": [
                1049, 
                344, 
                15, 
                37
            ], 
            "bboxVis": [
                1052, 
                345, 
                12, 
                10
            ], 
            "label": "pedestrian"
        }, 
        {
            "instanceId": 24002, 
            "bbox": [
                1063, 
                344, 
                15, 
                36
            ], 
            "bboxVis": [
                1069, 
                344, 
                6, 
                9
            ], 
            "label": "pedestrian"
        }, 
        {
            "instanceId": 24003, 
            "bbox": [
                1076, 
                346, 
                14, 
                33
            ], 
            "bboxVis": [
                1081, 
                347, 
                6, 
                5
            ], 
            "label": "pedestrian"
        }, 
        {
            "instanceId": 24004, 
            "bbox": [
                1146, 
                331, 
                20, 
                48
            ], 
            "bboxVis": [
                1152, 
                332, 
                8, 
                11
            ], 
            "label": "pedestrian"
        }, 
        {
            "instanceId": 24005, 
            "bbox": [
                1122, 
                341, 
                16, 
                39
            ], 
            "bboxVis": [
                1128, 
                342, 
                7, 
                3
            ], 
            "label": "pedestrian"
        }
    ]
}