{
    "imgHeight": 1024, 
    "imgWidth": 2048, 
    "objects": [
        {
            "instanceId": 24000, 
            "bbox": [
                568, 
                329, 
                9, 
                22
            ], 
            "bboxVis": [
                568, 
                330, 
                9, 
                9
            ], 
            "label": "pedestrian"
        }, 
        {
            "instanceId": 24001, 
            "bbox": [
                532, 
                331, 
                9, 
                22
            ], 
            "bboxVis": [
                534, 
                333, 
                7, 
                10
            ], 
            "label": "pedestrian"
        }, 
        {
            "instanceId": 24002, 
            "bbox": [
                519, 
                329, 
                11, 
                26
            ], 
            "bboxVis": [
                522, 
                329, 
                8, 
                18
            ], 
            "label": "pedestrian"
        }, 
        {
            "instanceId": 24003, 
            "bbox": [
                304, 
                320, 
                69, 
                170
            ], 
            "bboxVis": [
                328, 
                320, 
                41, 
                170
            ], 
            "label": "pedestrian"
        }, 
        {
            "instanceId": 24004, 
            "bbox": [
                1341, 
                362, 
                70, 
                171
            ], 
            "bboxVis": [
                1347, 
                363, 
                64, 
                170
            ], 
            "label": "pedestrian"
        }, 
        {
            "instanceId": 0, 
            "bbox": [
                253, 
                319, 
                24, 
                20
            ], 
            "bboxVis": [
                253, 
                319, 
                24, 
                20
            ], 
            "label": "ignore"
        }, 
        {
            "instanceId": 0, 
            "bbox": [
                227, 
                322, 
                10, 
                11
            ], 
            "bboxVis": [
                227, 
                322, 
                10, 
                11
            ], 
            "label": "ignore"
        }, 
        {
            "instanceId": 0, 
            "bbox": [
                182, 
                317, 
                35, 
                14
            ], 
            "bboxVis": [
                182, 
                317, 
                35, 
                14
            ], 
            "label": "ignore"
        }, 
        {
            "instanceId": 0, 
            "bbox": [
                164, 
                317, 
                7, 
                14
            ], 
            "bboxVis": [
                164, 
                317, 
                7, 
                14
            ], 
            "label": "ignore"
        }, 
        {
            "instanceId": 0, 
            "bbox": [
                250, 
                359, 
                8, 
                8
            ], 
            "bboxVis": [
                250, 
                359, 
                8, 
                8
            ], 
            "label": "ignore"
        }, 
        {
            "instanceId": 0, 
            "bbox": [
                76, 
                311, 
                57, 
                16
            ], 
            "bboxVis": [
                76, 
                311, 
                57, 
                16
            ], 
            "label": "ignore"
        }, 
        {
            "instanceId": 0, 
            "bbox": [
                8, 
                306, 
                51, 
                19
            ], 
            "bboxVis": [
                8, 
                306, 
                51, 
                19
            ], 
            "label": "ignore"
        }, 
        {
            "instanceId": 0, 
            "bbox": [
                388, 
                322, 
                10, 
                6
            ], 
            "bboxVis": [
                388, 
                322, 
                10, 
                6
            ], 
            "label": "ignore"
        }, 
        {
            "instanceId": 0, 
            "bbox": [
                249, 
                394, 
                14, 
                22
            ], 
            "bboxVis": [
                249, 
                394, 
                14, 
                22
            ], 
            "label": "ignore"
        }, 
        {
            "instanceId": 0, 
            "bbox": [
                235, 
                394, 
                13, 
                21
            ], 
            "bboxVis": [
                235, 
                394, 
                13, 
                21
            ], 
            "label": "ignore"
        }
    ]
}